superagi/__init__.py
superagi/tools/__init__.py
superagi/tools/base_tool.py
superagi/types/__init__.py
superagi/types/key_type.py
superagi_tools-1.0.8.dist-info/LICENSE
superagi_tools-1.0.8.dist-info/METADATA
superagi_tools-1.0.8.dist-info/WHEEL
superagi_tools-1.0.8.dist-info/top_level.txt
superagi_tools-1.0.8.dist-info/RECORD
