Metadata-Version: 2.1
Name: superagi-tools
Version: 1.0.8
Summary: superagi-tools is a python library specifically designed for developers working with SuperAGI. The library offers the BaseToolkit and BaseTool classes, requierd for development of custom tools and toolkits for SuperAGI.
Author: superagi
Author-email: mukunda@superagi.com
License-File: LICENSE
Requires-Dist: pydantic (==1.10.8)
Requires-Dist: PyYAML (==6.0)
